qtl_metrics/__init__.py
qtl_metrics-1.0.1.dist-info/WHEEL
qtl_metrics-1.0.1.dist-info/METADATA
qtl_metrics-1.0.1.dist-info/RECORD
